Metadata-Version: 2.1
Name: micropython-mpu6886
Version: 0.1.0
Summary: MicroPython I2C driver for MPU6886 6-axis motion tracking device
Home-page: https://github.com/tuupola/micropython-mpu6886
Author: Mika Tuupola
Author-email: tuupola@appelsiini.net
Maintainer: Mika Tuupola
Maintainer-email: tuupola@appelsiini.net
License: MIT
Keywords: accelerometer,gyro,micropython,i2c
Platform: UNKNOWN
Classifier: Development Status :: 4 - Beta
Classifier: Programming Language :: Python :: Implementation :: MicroPython
Classifier: License :: OSI Approved :: MIT License
